optimix/__init__.py
optimix/_check_grad.py
optimix/_exception.py
optimix/_function.py
optimix/_testit.py
optimix/_types.py
optimix/_variables.py
optimix-3.0.6.dist-info/LICENSE.md
optimix-3.0.6.dist-info/METADATA
optimix-3.0.6.dist-info/WHEEL
optimix-3.0.6.dist-info/RECORD
